Metadata-Version: 2.1
Name: swiftype-enterprise
Version: 1.0.1
Summary: A Deprecated API client for Swiftype Enterprise Search. Use elastic_enterprise_search instead.
Home-page: https://github.com/swiftype/swiftype-enterprise-python
Author: Swiftype
Author-email: eng@swiftype.com
License: MIT
Keywords: swiftype enterprise search api
Platform: UNKNOWN
Classifier: Development Status :: 4 - Beta
Classifier: Intended Audience :: Developers
Classifier: License :: OSI Approved :: MIT License
Classifier: Programming Language :: Python :: 2
Classifier: Programming Language :: Python :: 2.7
Classifier: Programming Language :: Python :: 3
Classifier: Programming Language :: Python :: 3.3
Classifier: Programming Language :: Python :: 3.4
Classifier: Programming Language :: Python :: 3.5
Provides-Extra: test
